fruitbot/__init__.py
fruitbot/enums.py
fruitbot/exceptions.py
fruitbot/models.py
fruitbot/client/__init__.py
fruitbot/client/client.py
fruitbot/configs/__init__.py
fruitbot/configs/configs.py
fruitbot/crypto/__init__.py
fruitbot/crypto/crypto.py
fruitbot/data/__init__.py
fruitbot/network/__init__.py
fruitbot/network/fc_socket.py
fruitbot/network/network.py
fruitbot/session/__init__.py
fruitbot/session/session.py
fruitbot/utils/__init__.py
fruitbot/utils/utils.py
fruitbot-1.6.1.dist-info/LICENSE
fruitbot-1.6.1.dist-info/METADATA
fruitbot-1.6.1.dist-info/WHEEL
fruitbot-1.6.1.dist-info/top_level.txt
fruitbot-1.6.1.dist-info/RECORD
