Metadata-Version: 2.2
Name: fruitbot
Version: 1.6.1
Summary: A simple, easy-to-use and powerful library for automating gameplay in the Fruit Craft game through APIs.
Home-page: https://github.com/AmirSF01/fruitcraft
Author: Amir S.Farahani
Project-URL: Homepage, https://github.com/AmirSF01/fruitcraft
Project-URL: Documentation, https://t.me/FruitcraftLib
Project-URL: Community, https://t.me/fruitbotGP
Keywords: fruit craft,fruitcraft,fruitbot,bot,api,client,automation,card,game
Classifier: Programming Language :: Python :: 3.7
Classifier: Programming Language :: Python :: 3.8
Classifier: Programming Language :: Python :: 3.9
Classifier: Programming Language :: Python :: 3.10
Classifier: Programming Language :: Python :: 3.11
Classifier: Programming Language :: Python :: 3.12
Classifier: Programming Language :: Python :: 3.13
Classifier: License :: OSI Approved :: MIT License
Classifier: Operating System :: OS Independent
Classifier: Topic :: Internet
Classifier: Topic :: Software Development :: Libraries
Classifier: Topic :: Software Development :: Libraries :: Python Modules
Classifier: Topic :: Games/Entertainment
Classifier: Topic :: Games/Entertainment :: Real Time Strategy
Requires-Python: >=3.7
License-File: LICENSE
Requires-Dist: urllib3
Requires-Dist: colorama
Dynamic: author
Dynamic: classifier
Dynamic: description
Dynamic: description-content-type
Dynamic: home-page
Dynamic: keywords
Dynamic: project-url
Dynamic: requires-dist
Dynamic: requires-python
Dynamic: summary
